[
    {
        "question": "How are you?",
        "questionNumber": 1,
        "options": [
            {
                "optionOne": "yes",
                "optionTwo": "no",
                "optionThree": "good",
                "optionFour": "ela",
                "rightAnswer": "yes"
            }
        ]
    },
    {
        "question": "What is you name"
        "questionNumber": 2,
        "options": [
            {
                "optionOne": "yes",
                "optionTwo": "no",
                "optionThree": "good",
                "optionFour": "ela",
                "rightAnswer": "yes"
            }
        ]
    },
    {
        "question": "What is you purpose of visit?",
        "questionNumber": 3,
        "options": [
            {
                "optionOne": "yes",
                "optionTwo": "no",
                "optionThree": "good",
                "optionFour": "ela",
                "rightAnswer": "yes"
            }
        ]
    }
]
